yatracker/__init__.py
yatracker/exceptions.py
yatracker/tracker/__init__.py
yatracker/tracker/api.py
yatracker/tracker/base.py
yatracker/tracker/client.py
yatracker/tracker/categories/__init__.py
yatracker/tracker/categories/attached_files.py
yatracker/tracker/categories/bulk_operations.py
yatracker/tracker/categories/checklists.py
yatracker/tracker/categories/comments.py
yatracker/tracker/categories/components.py
yatracker/tracker/categories/external_links.py
yatracker/tracker/categories/import_.py
yatracker/tracker/categories/issue_boards.py
yatracker/tracker/categories/issue_fields.py
yatracker/tracker/categories/issues.py
yatracker/tracker/categories/macros.py
yatracker/tracker/categories/priorities.py
yatracker/tracker/categories/projects.py
yatracker/tracker/categories/queues.py
yatracker/tracker/categories/users.py
yatracker/tracker/categories/worklogs.py
yatracker/types/__init__.py
yatracker/types/attachment.py
yatracker/types/base.py
yatracker/types/comment.py
yatracker/types/duration.py
yatracker/types/full_issue.py
yatracker/types/full_queue.py
yatracker/types/issue.py
yatracker/types/issue_link.py
yatracker/types/issue_type.py
yatracker/types/issue_type_config.py
yatracker/types/mixins.py
yatracker/types/priority.py
yatracker/types/queue.py
yatracker/types/queue_field.py
yatracker/types/queue_field_options_provider.py
yatracker/types/queue_field_query_provider.py
yatracker/types/queue_field_schema.py
yatracker/types/queue_version.py
yatracker/types/resolution.py
yatracker/types/sprint.py
yatracker/types/status.py
yatracker/types/transition.py
yatracker/types/transitions.py
yatracker/types/user.py
yatracker/types/workflow.py
yatracker/types/worklog.py
yatracker/utils/__init__.py
yatracker/utils/camel_case.py
yatracker-2024.4.2.dist-info/METADATA
yatracker-2024.4.2.dist-info/WHEEL
yatracker-2024.4.2.dist-info/licenses/LICENSE
yatracker-2024.4.2.dist-info/RECORD
