Metadata-Version: 2.3
Name: yatracker
Version: 2024.4.2
Summary: Async client for Yandex Tracker API
Project-URL: Repository, https://github.com/Olegt0rr/YaTracker/
Project-URL: Documentation, https://olegt0rr.github.io/YaTracker/
Author-email: Oleg Abramov <oleg@trueweb.app>
Maintainer-email: Oleg Abramov <oleg@trueweb.app>
License-Expression: MIT
License-File: LICENSE
Keywords: API,Tracker,Yandex,async
Classifier: Development Status :: 3 - Alpha
Classifier: Framework :: AsyncIO
Classifier: Intended Audience :: Developers
Classifier: License :: OSI Approved :: MIT License
Classifier: Programming Language :: Python
Classifier: Programming Language :: Python :: 3.10
Classifier: Programming Language :: Python :: 3.11
Classifier: Programming Language :: Python :: Implementation :: CPython
Classifier: Topic :: Software Development :: Libraries :: Application Frameworks
Classifier: Typing :: Typed
Requires-Python: >=3.10
Requires-Dist: aiohttp<3.10.0,>=3.8.5
Requires-Dist: certifi>=2023
Requires-Dist: msgspec~=0.18.2
Provides-Extra: dev
Requires-Dist: mypy>=1; extra == 'dev'
Requires-Dist: pre-commit>=3; extra == 'dev'
Requires-Dist: ruff>=0; extra == 'dev'
Provides-Extra: docs
Requires-Dist: mkdocs-material; extra == 'docs'
Requires-Dist: mkdocstrings[python]; extra == 'docs'
Provides-Extra: test
Requires-Dist: coverage>=7; extra == 'test'
Requires-Dist: pytest-asyncio>=0; extra == 'test'
Requires-Dist: pytest-cov>=4; extra == 'test'
Requires-Dist: pytest>=7; extra == 'test'
